LICENSE
README.md
setup.cfg
setup.py
pyblinkpico_text/__init__.py
pyblinkpico_text/pyblinkpico_text.py
pyblinkpico_text.egg-info/PKG-INFO
pyblinkpico_text.egg-info/SOURCES.txt
pyblinkpico_text.egg-info/dependency_links.txt
pyblinkpico_text.egg-info/requires.txt
pyblinkpico_text.egg-info/top_level.txt