Metadata-Version: 2.1
Name: pyblinkpico-text
Version: 0.1.0
Summary: The BlinkPico text library
Home-page: https://github.com/ID220/BlinkPico-Text
Author: Nishant Nepal & Andrea Bianchi
Author-email: andrea@kaist.ac.kr
License: MIT
Keywords: education,matrix_shield,HT16K33,RPI Pico
Platform: UNKNOWN
Classifier: Intended Audience :: Education
Classifier: Programming Language :: Python :: Implementation :: MicroPython
License-File: LICENSE
